tfhealthchecks/__init__.py
tfhealthchecks/healthcheck.py
tfhealthchecks/library.py
tfhealthchecks/utils.py
tfhealthchecks/checks/__init__.py
tfhealthchecks/checks/couchdb.py
tfhealthchecks/checks/httpcheck.py
tfhealthchecks-1.0.3.dist-info/METADATA
tfhealthchecks-1.0.3.dist-info/WHEEL
tfhealthchecks-1.0.3.dist-info/top_level.txt
tfhealthchecks-1.0.3.dist-info/RECORD
