Metadata-Version: 2.2
Name: tfhealthchecks
Version: 1.0.3
Summary: Library of health checks
Home-page: https://github.com/takeoff-com/tfhealthcheck-py
Author: sergey.yashchenko
Author-email: sergey.yashchenko@takeoff.com
Requires-Dist: requests
Requires-Dist: pytest
Dynamic: author
Dynamic: author-email
Dynamic: description
Dynamic: description-content-type
Dynamic: home-page
Dynamic: requires-dist
Dynamic: summary
